http_extended_client/__init__.py
http_extended_client/client.py
http_extended_client/models.py
http_extended_client-0.1.3.dist-info/LICENSE
http_extended_client-0.1.3.dist-info/METADATA
http_extended_client-0.1.3.dist-info/WHEEL
http_extended_client-0.1.3.dist-info/RECORD
