Metadata-Version: 2.3
Name: http_extended_client
Version: 0.1.3
Summary: 
Author: Bakminstof
Author-email: bakminstof@yandex.ru
Requires-Python: >=3.11,<4.0
Classifier: Programming Language :: Python :: 3
Classifier: Programming Language :: Python :: 3.11
Classifier: Programming Language :: Python :: 3.12
Classifier: Programming Language :: Python :: 3.13
Requires-Dist: httpx[http2] (>=0.28.1,<0.29.0)
